{
    "title": "Avaliação dos métodos de inspeção para atendimento às normas do sistema de gestão predial",
    "url": "https://ojs.brazilianjournals.com.br/ojs/index.php/BRJD/article/view/2500",
    "authors": "SE Pilz, MF Costella… - Brazilian Journal of …, 2019 - ojs.brazilianjournals.com.br",
    "abstract": "… de gestão de manutenção predial. As principais contribuições são a ajuda no entendimento \nde questões como a necessária qualificação profissional, dependendo do objetivo da …",
    "year": "2019",
    "source": "Google Scholar",
    "language": "pt",
    "id": "3487efdf86b1b22ed0bc4983fe65f319",
    "collected_at": "2025-03-05T09:26:18.990605"
}